code_ninja/__init__.py
code_ninja/py.typed
code_ninja-0.1.20.dist-info/WHEEL
code_ninja-0.1.20.dist-info/METADATA
code_ninja-0.1.20.dist-info/RECORD
