Metadata-Version: 2.3
Name: code-ninja
Version: 0.1.20
Summary: Code-ninja is the error handler library and help to detect the error and after detect the error give the solution of error.
Author: Asad Maqbool
Author-email: Asad Maqbool <asadmaqbool639@gmail.com>
Requires-Dist: openai
Requires-Dist: dotenv
Requires-Dist: rich
Requires-Python: >=3.11
